skewsentry/__init__.py
skewsentry/align.py
skewsentry/cli.py
skewsentry/compare.py
skewsentry/errors.py
skewsentry/inputs.py
skewsentry/report.py
skewsentry/runner.py
skewsentry/spec.py
skewsentry/utils.py
skewsentry/adapters/__init__.py
skewsentry/adapters/base.py
skewsentry/adapters/http.py
skewsentry/adapters/python.py
skewsentry-0.1.1.dist-info/licenses/LICENSE
skewsentry-0.1.1.dist-info/METADATA
skewsentry-0.1.1.dist-info/WHEEL
skewsentry-0.1.1.dist-info/entry_points.txt
skewsentry-0.1.1.dist-info/top_level.txt
skewsentry-0.1.1.dist-info/RECORD
