Metadata-Version: 2.4
Name: skewsentry
Version: 0.1.1
Summary: Catch training ↔ serving feature skew before you ship to production
Author-email: Yasser El Haddar <yasserelhaddar@gmail.com>
License: MIT License
Keywords: ml,machine-learning,feature-engineering,data-validation,mlops,feature-store,training,serving,parity,testing
Classifier: Development Status :: 4 - Beta
Classifier: Intended Audience :: Developers
Classifier: Topic :: Software Development :: Libraries :: Python Modules
Classifier: Topic :: Software Development :: Quality Assurance
Classifier: Topic :: Scientific/Engineering :: Artificial Intelligence
Classifier: Programming Language :: Python :: 3
Classifier: Programming Language :: Python :: 3 :: Only
Classifier: Programming Language :: Python :: 3.9
Classifier: Programming Language :: Python :: 3.10
Classifier: Programming Language :: Python :: 3.11
Classifier: Programming Language :: Python :: 3.12
Classifier: License :: OSI Approved :: MIT License
Classifier: Operating System :: OS Independent
Requires-Python: >=3.9
License-File: LICENSE
Requires-Dist: pandas>=2.0
Requires-Dist: pyarrow>=12
Requires-Dist: pydantic>=2
Requires-Dist: typer>=0.12
Requires-Dist: jinja2>=3
Requires-Dist: pyyaml>=6
Requires-Dist: requests>=2
Provides-Extra: dev
Requires-Dist: pytest>=7.0; extra == "dev"
Requires-Dist: pytest-cov>=4.1; extra == "dev"
Requires-Dist: scipy>=1.9; extra == "dev"
Requires-Dist: tabulate>=0.9; extra == "dev"
Requires-Dist: rich>=13.0; extra == "dev"
Requires-Dist: build>=1.0.3; extra == "dev"
Requires-Dist: orjson>=3.9; platform_python_implementation != "PyPy" and extra == "dev"
Requires-Dist: ipykernel>=6.29.0; extra == "dev"
Dynamic: license-file
